objson/__init__.py
objson/serializer.py
objson/version.py
objson_py-0.2.0.dist-info/LICENSE
objson_py-0.2.0.dist-info/METADATA
objson_py-0.2.0.dist-info/WHEEL
objson_py-0.2.0.dist-info/top_level.txt
objson_py-0.2.0.dist-info/RECORD
