Metadata-Version: 2.1
Name: objson-py
Version: 0.2.0
Summary: objson is a object serializer that enables you to convert object <-> json/dict
Home-page: https://github.com/uezo/objson
Author: uezo
Author-email: uezo@uezo.net
Maintainer: uezo
Maintainer-email: uezo@uezo.net
License: MIT
Platform: UNKNOWN
Classifier: Programming Language :: Python :: 3
